aionuts/__init__.py
aionuts/bot.py
aionuts/executor.py
aionuts/types.py
aionuts/dispatcher/__init__.py
aionuts/dispatcher/dispatcher.py
aionuts/dispatcher/filters.py
aionuts/dispatcher/handler.py
aionuts/dispatcher/middlewares.py
aionuts/utils/__init__.py
aionuts/utils/colors.py
aionuts/utils/utils.py
aionuts-0.0.5.dist-info/LICENSE
aionuts-0.0.5.dist-info/METADATA
aionuts-0.0.5.dist-info/WHEEL
aionuts-0.0.5.dist-info/top_level.txt
aionuts-0.0.5.dist-info/RECORD
