Metadata-Version: 2.1
Name: aionuts
Version: 0.0.5
Summary: framework for vk api
Home-page: https://github.com/filimanistr/aionuts
Author: filimanistr
Author-email: filimanistr@gmail.com
License: MIT
License-File: LICENSE
Requires-Dist: aiohttp
